{
  "surah": 161,
  "name": "The original meaning of kufr is to conceal. This lent the word a nuance of denial and it",
  "english_name": "",
  "introduction": "began to be used as an antonym of iman . Iman means to believe, to accept, and to recognize.\nKufr, on the contrary, denotes refusal to believe, to deny, to reject. According to the Qur'an\nthere are several possible forms of disbelief. One is to refuse either to believe in the existence\nof God, to acknowledge His sovereignty, to recognize Him as the only Lord of the Universe\nand of mankind or to recognize Him as the only Lord and the only object of worship and\nadoration. The second form of disbelief is when a man recognizes the existence of God but\nstill refuses to accept His ordinances and directives as the only source of true guidance, and\nas the true law for his life. The third form of disbelief is when even though a man recognizes\nin principle that he ought to follow the guidance of God he refuses to believe in the Prophets\nwho were the means of communicating God's guidance to man. The fourth form of disbelief\nis to differentiate between one Prophet and another and, out of parochialism and bigotry, to\naccept some Prophets and reject others. The fifth form of disbelief is the refusal to recognize,\neither totally or partially, the teachings communicated by the Prophets, on God's behalf,\nconcerning the beliefs, the principles of morality, and the laws for fashioning human life.\nThe sixth form of disbelief is where a person theoretically accepts all that he should accept\nbut wilfully disobeys God's ordinances and persists in this disobedience, and considers\ndisobedience rather than obedience to God to be the true principle of life.\nAll these modes of thought and action are forms of rebellion towards God and the Qur'an\ncharacterizes each of them as kufr. In addition, the term kufr is used at several places in the\nQur'an in the sense of ingratitude and in this usage it signifies the exact opposite of shukr\n(gratitude). Gratefulness consists in feeling thankful to one's benefactor, in duly recognizing\nthe value of his benevolence, in making use of it in a manner pleasing to its bestower, and in\nbeing utterly loyal to him. Ingratitude denotes, on the contrary, that the man concerned has\neither failed to recognize the bounty of his benefactor, or considers it to be either the\noutcome of his own power and ability or else that of some other person's favour or\nintercession. Another form of ingratitude consists in failing to recognize fully the worth of\nthe bounty received and in either allowing it to be wasted or to be used in contravention of\nthe will of the benefactor; this ingratitude includes infidelity and treachery towards the\nbenefactor in disregard of his benevolence and kindness. This kind of kufr is known in\nordinary language as ungratefulness.\nA\n162 @33b8 aSoelicll ace GZS Goods",
  "verses": []
}