{
  "surah": 163,
  "name": "There are certain attributes which belong exclusively to God. Moreover, there are",
  "english_name": "",
  "introduction": "certain duties that man owes to God by virtue of His being his Lord. The indictment of the\nQur'an is that the people in question ascribe to others than God the attributes which are\nexclusively His and likewise consider others to be the rightful claimants of certain rights\nover man which belong only to God. To be Lord of the entire complex of causal\nrelationships found in the universe, to dispense the needs and requirements of people, to\ndeliver them from distress and affliction, to heed complaints and respond to lamentations\nand prayers, and having full knowledge of all that is apparent as well as all that is hidden,\nare the exclusive attributes of God.\nFurthermore, there are certain rights which God alone may claim: that His creatures should\nrecognize Him alone as their Sovereign, prostrate themselves before Him alone in\nrecognition of their bondage to Him, turn to Him alone for the fulfilment of their prayers,\ncall Him alone for help and succour, place their trust is none save Him, centre their hopes\nand expectations only in His Munificence, and fear Him alone both in public and in private.\nIn the same way, being the only Absolute Sovereign of the universe, it befits none save God\nto lay down what is permitted and what is prohibited for His subjects, to prescribe their\nrights and duties, to command them what to do and what not to do, to direct them as to\nhow the energy and resources bestowed on them, by God, should be expended.\nAgain, it is God alone Who can ask His subjects to acknowledge His sovereignty, to accept\nHis commands as the source of law, to consider Him alone to be the Lord entitled to\ncommand men, to consider His commands supreme, and to turn to Him alone for correct\nguidance. Whoever either ascribes to any being other than God any of the aforementioned\nattributes or recognizes the claim of anyone save God to be entitled to any of the above-\nmentioned rights over His creatures is in fact setting up that being as a rival to God, and\nplacing him on the same plane as God. By the same token, any individual or institution\nclaiming to possess any of the exclusive attributes and rights of God (as mentioned above),\nis in fact claiming a position parallel and equal to that of God even though the claim to\ngodhead may not have been categorically spelled out.",
  "verses": []
}