{
  "surah": 246,
  "name": "Some jurists have interpreted this verse to signify that if the spouses break their vow",
  "english_name": "",
  "introduction": "and re-establish sexual relations they will not be liable to any expiation and will be\npardoned by God gratuitously. However, the majority of jurists are of the opinion that they,\nare required to expiate. The statement that God is Oft-Forgiving and Merciful does not mean\nthat God has forgiven them. It means rather that God will accept their expiation and will\nforgive them for whatever excesses they may have committed against each other.\n4 2 lp aepe yp rf wae\n227 saleasanl EG GMB A343",
  "verses": []
}